<?xml version="1.0" encoding="iso-8859-1"?>
<root version="3.3" release="8|CoreRPG:4">
	<character>
		<abilities>
			<charisma>
				<bonus type="number">-1</bonus>
				<save type="number">-1</save>
				<savemodifier type="number">0</savemodifier>
				<saveprof type="number">0</saveprof>
				<score type="number">8</score>
			</charisma>
			<constitution>
				<bonus type="number">3</bonus>
				<save type="number">3</save>
				<savemodifier type="number">0</savemodifier>
				<saveprof type="number">0</saveprof>
				<score type="number">16</score>
			</constitution>
			<dexterity>
				<bonus type="number">4</bonus>
				<save type="number">7</save>
				<savemodifier type="number">0</savemodifier>
				<saveprof type="number">1</saveprof>
				<score type="number">18</score>
			</dexterity>
			<intelligence>
				<bonus type="number">1</bonus>
				<save type="number">4</save>
				<savemodifier type="number">0</savemodifier>
				<saveprof type="number">1</saveprof>
				<score type="number">13</score>
			</intelligence>
			<strength>
				<bonus type="number">0</bonus>
				<save type="number">0</save>
				<savemodifier type="number">0</savemodifier>
				<saveprof type="number">0</saveprof>
				<score type="number">10</score>
			</strength>
			<wisdom>
				<bonus type="number">1</bonus>
				<save type="number">1</save>
				<savemodifier type="number">0</savemodifier>
				<saveprof type="number">0</saveprof>
				<score type="number">12</score>
			</wisdom>
		</abilities>
		<adventurelist>
		</adventurelist>
		<age type="string">25</age>
		<alignment type="string">Chaotic Neutral</alignment>
		<appearance type="string">I am utterly serene, even in the face of disaster.\nMinor scar = No adverse effect. Magical Healing of 6th level or higher like regeneration or heal removes the scar. If you take another minor scar, then you are horribly scarred.</appearance>
		<backgroundlink type="windowreference">
			<class></class>
			<recordname></recordname>
		</backgroundlink>
		<bonds type="string">I will become the greatest thief that ever lived.</bonds>
		<classes>
			<id-00001>
				<casterlevelinvmult type="number">0</casterlevelinvmult>
				<casterpactmagic type="number">0</casterpactmagic>
				<hddie type="dice">d8</hddie>
				<hdused type="number">3</hdused>
				<level type="number">6</level>
				<name type="string">Rogue</name>
				<rolls>
					<lvl-001 type="number">8</lvl-001>
					<lvl-002 type="number">8</lvl-002>
					<lvl-003 type="number">8</lvl-003>
					<lvl-004 type="number">8</lvl-004>
					<lvl-005 type="number">4</lvl-005>
					<lvl-006 type="number">2</lvl-006>
				</rolls>
				<shortcut type="windowreference">
					<class>reference_class</class>
					<recordname>reference.classdata.rogue@DD PHB Deluxe</recordname>
				</shortcut>
			</id-00001>
		</classes>
		<coins>
			<slot1>
				<amount type="number">0</amount>
				<name type="string">GP</name>
			</slot1>
			<slot2>
				<amount type="number">0</amount>
				<name type="string">EP</name>
			</slot2>
			<slot3>
				<amount type="number">0</amount>
				<name type="string">PP</name>
			</slot3>
			<slot4>
				<amount type="number">0</amount>
				<name type="string">SP</name>
			</slot4>
			<slot5>
				<amount type="number">0</amount>
				<name type="string">CP</name>
			</slot5>
			<slot6>
				<amount type="number">0</amount>
			</slot6>
		</coins>
		<defenses>
			<ac>
				<armor type="number">3</armor>
				<disstealth type="number">0</disstealth>
				<misc type="number">0</misc>
				<prof type="number">1</prof>
				<shield type="number">0</shield>
				<temporary type="number">0</temporary>
				<total type="number">17</total>
			</ac>
		</defenses>
		<deity type="string">Raven Queen</deity>
		<effectlist>
		</effectlist>
		<encumbrance>
			<encumbered type="number">50</encumbered>
			<encumberedheavy type="number">100</encumberedheavy>
			<liftpushdrag type="number">300</liftpushdrag>
			<load type="number">28</load>
			<max type="number">150</max>
		</encumbrance>
		<exp type="number">14063</exp>
		<expneeded type="number">23000</expneeded>
		<featlist>
			<id-00001>
				<locked type="number">1</locked>
				<name type="string">Valiant</name>
				<text type="formattedtext">
					<p>Spirited, intrepid, and prepared to rise to any challenge, you make a formidable combatant.</p>
					<p>You gain the following benefits:</p>
					<p>-Whenever you fail a saving throw against being frightened, you can immediately use your reaction to reroll this saving throw. The result of the second roll replaces the first.</p>
					<p>-You have a bonus to the attack and damage rolls of your melee weapon attacks against larger creatures. The bonus is equal to +1 for each size category between you and the creature.</p>
					<p>-Whenever a creature scores a critical hit against you, you can use your reaction to make a melee attack against a creature within range.</p>
				</text>
			</id-00001>
		</featlist>
		<featurelist>
			<id-00001>
				<level type="number">1</level>
				<locked type="number">1</locked>
				<name type="string">Thieves' Cant</name>
				<source type="string">Rogue</source>
				<text type="formattedtext">
					<p>During your rogue training you learned thieves' cant, a secret mix of dialect, jargon, and code that allows you to hide messages in seemingly normal conversation. Only another creature that knows thieves' cant understands such messages. It takes four times longer to convey such a message than it does to speak the same idea plainly.</p>
					<p>In addition, you understand a set of secret signs and symbols used to convey short, simple messages, such as whether an area is dangerous or the territory of a thieves' guild, whether loot is nearby, or whether the people in an area are easy marks or will provide a safe house for thieves on the run.</p>
				</text>
			</id-00001>
			<id-00002>
				<level type="number">1</level>
				<locked type="number">1</locked>
				<name type="string">Sneak Attack</name>
				<source type="string">Rogue</source>
				<text type="formattedtext">
					<p>Beginning at 1st level, you know how to strike subtly and exploit a foe's distraction. Once per turn, you can deal an extra 1d6 damage to one creature you hit with an attack if you have advantage on the attack roll. The attack must use a finesse or a ranged weapon.</p>
					<p>You don't need advantage on the attack roll if another enemy of the target is within 5 feet of it, that enemy isn't incapacitated, and you don't have disadvantage on the attack roll.</p>
					<p>The amount of the extra damage increases as you gain levels in this class, as shown in the Sneak Attack column of the Rogue table.</p>
				</text>
			</id-00002>
			<id-00003>
				<level type="number">1</level>
				<locked type="number">1</locked>
				<name type="string">Expertise</name>
				<source type="string">Rogue</source>
				<text type="formattedtext">
					<p>At 1st level, choose two of your skill proficiencies, or one of your skill proficiencies and your proficiency with thieves' tools. Your proficiency bonus is doubled for any ability check you make that uses either of the chosen proficiencies.</p>
					<p>At 6th level, you can choose two more of your proficiencies (in skills or with thieves' tools) to gain this benefit.</p>
				</text>
			</id-00003>
			<id-00004>
				<level type="number">2</level>
				<locked type="number">1</locked>
				<name type="string">Cunning Action</name>
				<source type="string">Rogue</source>
				<text type="formattedtext">
					<p>Starting at 2nd level, your quick thinking and agility allow you to move and act quickly. You can take a bonus action on each of your turns in combat. This action can be used only to take the Dash, Sleight of Hand, Disarm trap, pick lock, Use object or Hide action.</p>
				</text>
			</id-00004>
			<id-00005>
				<level type="number">1</level>
				<locked type="number">1</locked>
				<name type="string">Scout</name>
				<source type="string">Rogue</source>
				<text type="formattedtext">
					<p>You are skilled in stealth and surviving far from the streets of a city, allowing you to scout ahead of your companions during expeditions. Rogues who embrace this archetype are at home in the wilderness and among barbarians and rangers, and many Scouts serve as the eyes and ears of war bands. Ambusher, spy, bounty hunter-these are just a few of the roles that Scouts assume as they range the world.</p>
					<linklist>
						<link class="imagewindow" recordname="reference.imagedata.img_scout_jpg@DD Xanathar's Guide to Everything Players"><b>Image: </b>Scout</link>
					</linklist>
					<h>Features</h>
					<linklist>
						<link class="reference_classfeature" recordname="reference.classdata.rogue.features.skirmisher3@DD Xanathar's Guide to Everything Players">Skirmisher</link>
						<link class="reference_classfeature" recordname="reference.classdata.rogue.features.survivalist3@DD Xanathar's Guide to Everything Players">Survivalist</link>
						<link class="reference_classfeature" recordname="reference.classdata.rogue.features.superiormobility9@DD Xanathar's Guide to Everything Players">Superior Mobility</link>
						<link class="reference_classfeature" recordname="reference.classdata.rogue.features.ambushmaster13@DD Xanathar's Guide to Everything Players">Ambush Master</link>
						<link class="reference_classfeature" recordname="reference.classdata.rogue.features.suddenstrike17@DD Xanathar's Guide to Everything Players">Sudden Strike</link>
					</linklist>
				</text>
			</id-00005>
			<id-00006>
				<level type="number">3</level>
				<locked type="number">1</locked>
				<name type="string">Roguish Archetype</name>
				<source type="string">Rogue</source>
				<specializationchoice type="number">1</specializationchoice>
				<text type="formattedtext">
					<p>At 3rd level, you choose an archetype that you emulate in the exercise of your rogue abilities. Thief, Assassin or Arcane Trickster, all detailed at the end of the class description. Your archetype choice grants you features at 3rd level and then again at 9th, 13th, and 17th level.</p>
				</text>
			</id-00006>
			<id-00007>
				<level type="number">3</level>
				<locked type="number">1</locked>
				<name type="string">Survivalist</name>
				<source type="string">Rogue</source>
				<specialization type="string">Scout</specialization>
				<text type="formattedtext">
					<p>When you choose this archetype at 3rd level, you gain proficiency in the Nature and Survival skills if you don't already have it. Your proficiency bonus is doubled for any ability check you make that uses either of those proficiencies.</p>
				</text>
			</id-00007>
			<id-00008>
				<level type="number">3</level>
				<locked type="number">1</locked>
				<name type="string">Skirmisher</name>
				<source type="string">Rogue</source>
				<specialization type="string">Scout</specialization>
				<text type="formattedtext">
					<p>Starting at 3rd level, you are difficult to pin down during a fight. You can move up to half your speed as a reaction when an enemy ends its turn within 5 feet of you. This movement doesn't provoke opportunity attacks.</p>
				</text>
			</id-00008>
			<id-00009>
				<level type="number">4</level>
				<locked type="number">1</locked>
				<name type="string">Ability Score Improvement</name>
				<source type="string">Rogue</source>
				<text type="formattedtext">
					<p>When you reach 4th level, and again at 8th, 10th, 12th, 16th, and 19th level, you can increase one ability score of your choice by 2, or you can increase two ability scores of your choice by 1. As normal, you can't increase an ability score above 20 using this feature.</p>
				</text>
			</id-00009>
			<id-00010>
				<level type="number">5</level>
				<locked type="number">1</locked>
				<name type="string">Uncanny Dodge</name>
				<source type="string">Rogue</source>
				<text type="formattedtext">
					<p>Starting at 5th level, when an attacker that you can see hits you with an attack, you can use your reaction to halve the attack's damage against you.</p>
				</text>
			</id-00010>
		</featurelist>
		<flaws type="string">You are always icy cold to the touch.</flaws>
		<gender type="string">Male</gender>
		<hero type="number">0</hero>
		<hp>
			<adjust type="number">0</adjust>
			<base type="number">56</base>
			<deathsavefail type="number">3</deathsavefail>
			<deathsavesuccess type="number">0</deathsavesuccess>
			<hdmod type="number">0</hdmod>
			<temporary type="number">0</temporary>
			<total type="number">56</total>
			<wounds type="number">56</wounds>
		</hp>
		<ideals type="string">I stood alone against a terrible monster.</ideals>
		<initiative>
			<misc type="number">0</misc>
			<temporary type="number">0</temporary>
			<total type="number">4</total>
		</initiative>
		<inspiration type="number">0</inspiration>
		<inventorylist>
			<id-00001>
				<ac type="number">13</ac>
				<bonus type="number">0</bonus>
				<carried type="number">2</carried>
				<cost type="string">45 gp</cost>
				<count type="number">1</count>
				<description type="formattedtext">
					<linklist>
						<link class="imagewindow" recordname="image.id-02109">studded_leather</link>
					</linklist>
					<p>Made from supple and thin materials, light armor favors agile adventurers since it offers some protection without sacrificing mobility. If you wear light armor, you add your Dexterity modifier to the base number from your armor type to determine your Armor Class.</p>
					<p>Made from tough but flexible leather, studded leather is reinforced with close-set rivets or spikes.</p>
				</description>
				<dexbonus type="string">Yes</dexbonus>
				<effectlist>
					<id-00001>
						<ability_modifier type="number">0</ability_modifier>
						<actiononly type="number">0</actiononly>
						<durdice type="dice"></durdice>
						<durmod type="number">0</durmod>
						<effect type="string">CHECK: -1, strength, dexterity</effect>
						<effect_description type="string">[CHECK: -1, strength, dexterity] visibility [show]</effect_description>
						<misc_modifier type="number">0</misc_modifier>
						<name type="string">Studded Leather Armor</name>
						<save_modifier type="number">0</save_modifier>
						<susceptiblity_modifier type="number">0</susceptiblity_modifier>
						<visibility type="string">show</visibility>
					</id-00001>
				</effectlist>
				<isidentified type="number">1</isidentified>
				<locked type="number">1</locked>
				<name type="string">Studded Leather Armor</name>
				<nonidentified type="string">Dex 4 max</nonidentified>
				<stealth type="string">-</stealth>
				<strength type="string">-</strength>
				<subtype type="string">Light Armor</subtype>
				<type type="string">Armor</type>
				<weight type="number">15</weight>
			</id-00001>
			<id-00002>
				<carried type="number">2</carried>
				<cost type="string">10 gp</cost>
				<count type="number">2</count>
				<damage type="string">1d6 piercing</damage>
				<isidentified type="number">1</isidentified>
				<locked type="number">1</locked>
				<name type="string">Shortsword</name>
				<properties type="string">Finesse, light</properties>
				<subtype type="string">Martial Weapons</subtype>
				<type type="string">Weapon</type>
				<weight type="number">2</weight>
			</id-00002>
			<id-00003>
				<carried type="number">1</carried>
				<cost type="string">1 gp</cost>
				<count type="number">1</count>
				<description type="formattedtext">
					<p>A quiver can hold up to 20 arrows.</p>
				</description>
				<isidentified type="number">1</isidentified>
				<locked type="number">1</locked>
				<name type="string">Quiver</name>
				<subtype type="string">Standard</subtype>
				<type type="string">Adventuring Gear</type>
				<weight type="number">1</weight>
			</id-00003>
			<id-00004>
				<carried type="number">1</carried>
				<cost type="string">25 gp</cost>
				<count type="number">1</count>
				<damage type="string">1d6 piercing</damage>
				<isidentified type="number">1</isidentified>
				<locked type="number">1</locked>
				<name type="string">Shortbow</name>
				<properties type="string">Ammunition (range 80/320), two-handed</properties>
				<subtype type="string">Simple Ranged Weapons</subtype>
				<type type="string">Weapon</type>
				<weight type="number">2</weight>
			</id-00004>
			<id-00005>
				<carried type="number">1</carried>
				<cost type="string">1 gp</cost>
				<count type="number">1</count>
				<isidentified type="number">1</isidentified>
				<location type="string">quiver</location>
				<locked type="number">1</locked>
				<name type="string">Arrows (20)</name>
				<subtype type="string">Ammunition</subtype>
				<type type="string">Adventuring Gear</type>
				<weight type="number">1</weight>
			</id-00005>
			<id-00006>
				<carried type="number">1</carried>
				<cost type="string">2 sp</cost>
				<count type="number">1</count>
				<isidentified type="number">1</isidentified>
				<locked type="number">1</locked>
				<name type="string">Waterskin</name>
				<subtype type="string">Standard</subtype>
				<type type="string">Adventuring Gear</type>
				<weight type="number">5</weight>
			</id-00006>
		</inventorylist>
		<languagelist>
			<id-00001>
				<name type="string">Common</name>
			</id-00001>
			<id-00002>
				<name type="string">Elvish</name>
			</id-00002>
			<id-00003>
				<name type="string">Undercommon</name>
			</id-00003>
			<id-00004>
				<name type="string">Sylvan</name>
			</id-00004>
			<id-00005>
				<name type="string">Secret</name>
			</id-00005>
		</languagelist>
		<level type="number">6</level>
		<name type="string">Haggen de Merak</name>
		<notes type="string">Hit point rolls 8+8+8+4</notes>
		<pc_label_hero type="string">Hero Point</pc_label_hero>
		<perception type="number">17</perception>
		<perceptionmodifier type="number">0</perceptionmodifier>
		<personalitytraits type="string">There's nothing I like more than a good mystery.</personalitytraits>
		<powergroup>
		</powergroup>
		<powermeta>
			<pactmagicslots1>
				<max type="number">0</max>
				<used type="number">0</used>
			</pactmagicslots1>
			<pactmagicslots2>
				<max type="number">0</max>
				<used type="number">0</used>
			</pactmagicslots2>
			<pactmagicslots3>
				<max type="number">0</max>
				<used type="number">0</used>
			</pactmagicslots3>
			<pactmagicslots4>
				<max type="number">0</max>
				<used type="number">0</used>
			</pactmagicslots4>
			<pactmagicslots5>
				<max type="number">0</max>
				<used type="number">0</used>
			</pactmagicslots5>
			<pactmagicslots6>
				<max type="number">0</max>
				<used type="number">0</used>
			</pactmagicslots6>
			<pactmagicslots7>
				<max type="number">0</max>
				<used type="number">0</used>
			</pactmagicslots7>
			<pactmagicslots8>
				<max type="number">0</max>
				<used type="number">0</used>
			</pactmagicslots8>
			<pactmagicslots9>
				<max type="number">0</max>
				<used type="number">0</used>
			</pactmagicslots9>
			<spellslots1>
				<max type="number">0</max>
				<used type="number">0</used>
			</spellslots1>
			<spellslots2>
				<max type="number">0</max>
				<used type="number">0</used>
			</spellslots2>
			<spellslots3>
				<max type="number">0</max>
				<used type="number">0</used>
			</spellslots3>
			<spellslots4>
				<max type="number">0</max>
				<used type="number">0</used>
			</spellslots4>
			<spellslots5>
				<max type="number">0</max>
				<used type="number">0</used>
			</spellslots5>
			<spellslots6>
				<max type="number">0</max>
				<used type="number">0</used>
			</spellslots6>
			<spellslots7>
				<max type="number">0</max>
				<used type="number">0</used>
			</spellslots7>
			<spellslots8>
				<max type="number">0</max>
				<used type="number">0</used>
			</spellslots8>
			<spellslots9>
				<max type="number">0</max>
				<used type="number">0</used>
			</spellslots9>
		</powermeta>
		<powermode type="string">standard</powermode>
		<powers>
			<id-00001>
				<actions>
					<id-00001>
						<durmod type="number">1</durmod>
						<label type="string">RESIST: all</label>
						<order type="number">1</order>
						<targeting type="string">self</targeting>
						<tknbutton type="token"></tknbutton>
						<type type="string">effect</type>
					</id-00001>
					<id-00002>
						<durmod type="number">0</durmod>
						<label type="string">NOTE: Teleport 30 feet as a bonus action</label>
						<order type="number">2</order>
						<targeting type="string">self</targeting>
						<tknbutton type="token"></tknbutton>
						<type type="string">effect</type>
					</id-00002>
				</actions>
				<cast type="number">1</cast>
				<description type="formattedtext">
					<p>As a bonus action, you can magically teleport up to 30 feet to an unoccupied space you can see. Once you use this trait, you can't do so again until you finish a long rest.</p>
					<p></p>
					<p>Starting at 3rd level, you also gain resistance to all damage when you teleport using this trait. The resistance lasts until the start of your next turn. During that time, you appear ghostly and translucent.</p>
				</description>
				<level type="number">0</level>
				<locked type="number">1</locked>
				<name type="string">Blessing of the Raven Queen (bonus action)</name>
				<prepared type="number">1</prepared>
				<preparedDomain type="number">0</preparedDomain>
				<ritual type="number">0</ritual>
			</id-00001>
			<id-00002>
				<actions>
					<id-00001>
						<durmod type="number">0</durmod>
						<label type="string">IFT: SIZE(large);ATK:1; DMG:1</label>
						<order type="number">1</order>
						<targeting type="string">self</targeting>
						<tknbutton type="token"></tknbutton>
						<type type="string">effect</type>
					</id-00001>
					<id-00002>
						<durmod type="number">0</durmod>
						<label type="string">IFT: SIZE(huge);ATK:2;DMG:2</label>
						<order type="number">2</order>
						<targeting type="string">self</targeting>
						<tknbutton type="token"></tknbutton>
						<type type="string">effect</type>
					</id-00002>
					<id-00003>
						<durmod type="number">0</durmod>
						<label type="string">IFT:SIZE(gargantuan);ATK:3;DMG:3</label>
						<order type="number">3</order>
						<targeting type="string">self</targeting>
						<tknbutton type="token"></tknbutton>
						<type type="string">effect</type>
					</id-00003>
				</actions>
				<cast type="number">0</cast>
				<description type="formattedtext">
					<p></p>
				</description>
				<level type="number">0</level>
				<name type="string">Valiant bonus against larger creatures</name>
				<prepared type="number">0</prepared>
				<preparedDomain type="number">0</preparedDomain>
				<ritual type="number">0</ritual>
			</id-00002>
			<id-00003>
				<actions>
					<id-00001>
						<apply type="string">roll</apply>
						<durmod type="number">0</durmod>
						<label type="string">DMG: 3d6</label>
						<order type="number">1</order>
						<targeting type="string">self</targeting>
						<tknbutton type="token"></tknbutton>
						<type type="string">effect</type>
					</id-00001>
				</actions>
				<cast type="number">0</cast>
				<description type="formattedtext">
					<p></p>
				</description>
				<level type="number">0</level>
				<name type="string">Sneak Attack</name>
				<prepared type="number">0</prepared>
				<preparedDomain type="number">0</preparedDomain>
				<ritual type="number">0</ritual>
			</id-00003>
			<id-00004>
				<actions>
					<id-00001>
						<durmod type="number">0</durmod>
						<label type="string">RESIST: necrotic</label>
						<order type="number">1</order>
						<targeting type="string">self</targeting>
						<tknbutton type="token"></tknbutton>
						<type type="string">effect</type>
					</id-00001>
				</actions>
				<cast type="number">0</cast>
				<level type="number">0</level>
				<name type="string">Necrotic Resistance</name>
				<prepared type="number">0</prepared>
				<preparedDomain type="number">0</preparedDomain>
			</id-00004>
			<id-00005>
				<actions>
					<id-00001>
						<apply type="string">roll</apply>
						<durmod type="number">0</durmod>
						<label type="string">RESIST: all</label>
						<order type="number">1</order>
						<targeting type="string">self</targeting>
						<tknbutton type="token"></tknbutton>
						<type type="string">effect</type>
					</id-00001>
				</actions>
				<cast type="number">0</cast>
				<description type="formattedtext">
					<p>Starting at 5th level, when an attacker that you can see hits you with an attack, you can use your reaction to halve the attack's damage against you.</p>
				</description>
				<level type="number">0</level>
				<locked type="number">1</locked>
				<name type="string">Uncanny Dodge (reaction)</name>
				<prepared type="number">0</prepared>
				<preparedDomain type="number">0</preparedDomain>
				<ritual type="number">0</ritual>
			</id-00005>
			<id-00006>
				<actions>
					<id-00001>
						<durmod type="number">0</durmod>
						<label type="string">NOTE: move 15 ft as a reaction</label>
						<order type="number">1</order>
						<tknbutton type="token"></tknbutton>
						<type type="string">effect</type>
					</id-00001>
				</actions>
				<cast type="number">0</cast>
				<description type="formattedtext">
					<p>Starting at 3rd level, you are difficult to pin down during a fight. You can move up to half your speed as a reaction when an enemy ends its turn within 5 feet of you. This movement doesn't provoke opportunity attacks.</p>
				</description>
				<level type="number">0</level>
				<locked type="number">0</locked>
				<name type="string">Skirmisher (reaction)</name>
				<prepared type="number">0</prepared>
				<preparedDomain type="number">0</preparedDomain>
				<ritual type="number">0</ritual>
			</id-00006>
			<id-00007>
				<actions>
					<id-00001>
						<durmod type="number">0</durmod>
						<label type="string">Leatherworking; AC: 1</label>
						<order type="number">1</order>
						<targeting type="string">self</targeting>
						<tknbutton type="token"></tknbutton>
						<type type="string">effect</type>
					</id-00001>
				</actions>
				<cast type="number">0</cast>
				<level type="number">0</level>
				<name type="string">Leatherworking Tools</name>
				<prepared type="number">0</prepared>
				<preparedDomain type="number">0</preparedDomain>
			</id-00007>
		</powers>
		<profbonus type="number">3</profbonus>
		<proficiencylist>
			<id-00001>
				<name type="string">Weapon: Simple weapons, hand crossbows, longswords, rapiers, shortswords</name>
			</id-00001>
			<id-00002>
				<name type="string">Tool: Thieves' tools</name>
			</id-00002>
			<id-00003>
				<name type="string">Armor: Light armor</name>
			</id-00003>
		</proficiencylist>
		<race type="string">Elf (Shadar-kai)</race>
		<racelink type="windowreference">
			<class>reference_race</class>
			<recordname>reference.racedata.elf@DD Mordenkainen's Tome of Foes</recordname>
		</racelink>
		<senses type="string">Darkvision 60</senses>
		<shifttoken type="token"></shifttoken>
		<size type="string">Medium</size>
		<skilllist>
			<id-00001>
				<misc type="number">0</misc>
				<name type="string">Perception</name>
				<prof type="number">2</prof>
				<stat type="string">wisdom</stat>
				<total type="number">7</total>
			</id-00001>
			<id-00002>
				<misc type="number">0</misc>
				<name type="string">Acrobatics</name>
				<prof type="number">1</prof>
				<stat type="string">dexterity</stat>
				<total type="number">7</total>
			</id-00002>
			<id-00003>
				<misc type="number">0</misc>
				<name type="string">Investigation</name>
				<prof type="number">2</prof>
				<stat type="string">intelligence</stat>
				<total type="number">7</total>
			</id-00003>
			<id-00004>
				<misc type="number">0</misc>
				<name type="string">Stealth</name>
				<prof type="number">2</prof>
				<stat type="string">dexterity</stat>
				<total type="number">10</total>
			</id-00004>
			<id-00005>
				<misc type="number">0</misc>
				<name type="string">Arcana</name>
				<prof type="number">0</prof>
				<stat type="string">intelligence</stat>
				<total type="number">1</total>
			</id-00005>
			<id-00006>
				<misc type="number">0</misc>
				<name type="string">Persuasion</name>
				<prof type="number">0</prof>
				<stat type="string">charisma</stat>
				<total type="number">-1</total>
			</id-00006>
			<id-00007>
				<misc type="number">0</misc>
				<name type="string">Nature</name>
				<prof type="number">1</prof>
				<stat type="string">intelligence</stat>
				<total type="number">4</total>
			</id-00007>
			<id-00008>
				<misc type="number">0</misc>
				<name type="string">Medicine</name>
				<prof type="number">0</prof>
				<stat type="string">wisdom</stat>
				<total type="number">1</total>
			</id-00008>
			<id-00009>
				<misc type="number">0</misc>
				<name type="string">Survival</name>
				<prof type="number">1</prof>
				<stat type="string">wisdom</stat>
				<total type="number">4</total>
			</id-00009>
			<id-00010>
				<misc type="number">0</misc>
				<name type="string">Performance</name>
				<prof type="number">0</prof>
				<stat type="string">charisma</stat>
				<total type="number">-1</total>
			</id-00010>
			<id-00011>
				<misc type="number">0</misc>
				<name type="string">Religion</name>
				<prof type="number">0</prof>
				<stat type="string">intelligence</stat>
				<total type="number">1</total>
			</id-00011>
			<id-00012>
				<misc type="number">0</misc>
				<name type="string">Athletics</name>
				<prof type="number">2</prof>
				<stat type="string">strength</stat>
				<total type="number">6</total>
			</id-00012>
			<id-00013>
				<misc type="number">0</misc>
				<name type="string">Sleight of Hand</name>
				<prof type="number">1</prof>
				<stat type="string">dexterity</stat>
				<total type="number">7</total>
			</id-00013>
			<id-00014>
				<misc type="number">0</misc>
				<name type="string">Insight</name>
				<prof type="number">0</prof>
				<stat type="string">wisdom</stat>
				<total type="number">1</total>
			</id-00014>
			<id-00015>
				<misc type="number">0</misc>
				<name type="string">Intimidation</name>
				<prof type="number">0</prof>
				<stat type="string">charisma</stat>
				<total type="number">-1</total>
			</id-00015>
			<id-00016>
				<misc type="number">0</misc>
				<name type="string">Deception</name>
				<prof type="number">0</prof>
				<stat type="string">charisma</stat>
				<total type="number">-1</total>
			</id-00016>
			<id-00017>
				<misc type="number">0</misc>
				<name type="string">History</name>
				<prof type="number">0</prof>
				<stat type="string">intelligence</stat>
				<total type="number">1</total>
			</id-00017>
			<id-00018>
				<misc type="number">0</misc>
				<name type="string">Animal Handling</name>
				<prof type="number">0</prof>
				<stat type="string">wisdom</stat>
				<total type="number">1</total>
			</id-00018>
			<id-00019>
				<misc type="number">0</misc>
				<name type="string">Thieves' Tools</name>
				<prof type="number">1</prof>
				<stat type="string">dexterity</stat>
				<total type="number">7</total>
			</id-00019>
			<id-00020>
				<misc type="number">0</misc>
				<name type="string">Leatherworker&#180;s Tools</name>
				<prof type="number">1</prof>
				<stat type="string">dexterity</stat>
				<text type="formattedtext">
					<p></p>
				</text>
				<total type="number">7</total>
			</id-00020>
		</skilllist>
		<speed>
			<armor type="number">0</armor>
			<base type="number">30</base>
			<misc type="number">0</misc>
			<temporary type="number">0</temporary>
			<total type="number">30</total>
		</speed>
		<stats>
			<bigFoeCR type="number">4</bigFoeCR>
			<bigFoeName type="string">Yrthaak, juvenile</bigFoeName>
			<biggestDamage type="number">48</biggestDamage>
			<crits type="number">0</crits>
			<damage type="number">224</damage>
			<damageReceived type="number">111</damageReceived>
			<fumbles type="number">0</fumbles>
			<healing type="number">0</healing>
			<healingReceived type="number">16</healingReceived>
			<hits type="number">11</hits>
			<kills type="number">7</kills>
			<kos type="number">3</kos>
			<misses type="number">2</misses>
			<sessionbigFoeCR type="number">0</sessionbigFoeCR>
			<sessionbiggestDamage type="number">0</sessionbiggestDamage>
			<sessioncrits type="number">0</sessioncrits>
			<sessiondamage type="number">0</sessiondamage>
			<sessiondamageReceived type="number">0</sessiondamageReceived>
			<sessionfumbles type="number">0</sessionfumbles>
			<sessionhealing type="number">0</sessionhealing>
			<sessionhealingReceived type="number">0</sessionhealingReceived>
			<sessionhits type="number">0</sessionhits>
			<sessionkills type="number">0</sessionkills>
			<sessionkos type="number">0</sessionkos>
			<sessionmisses type="number">0</sessionmisses>
		</stats>
		<temp>
		</temp>
		<token type="token">portrait_id-00005_token</token>
		<traitlist>
			<id-00001>
				<locked type="number">1</locked>
				<name type="string">Trance</name>
				<source type="string">Elf</source>
				<text type="formattedtext">
					<p>Elves don't need to sleep. Instead, they meditate deeply, remaining semiconscious, for 4 hours a day. (The Common word for such meditation is &quot;trance.&quot;) While meditating, you can dream after a fashion; such dreams are actually mental exercises that have become reflexive through years of practice. After resting in this way, you gain the same benefit that a human does from 8 hours of sleep.</p>
				</text>
				<type type="string">racial</type>
			</id-00001>
			<id-00002>
				<locked type="number">1</locked>
				<name type="string">Keen Senses</name>
				<source type="string">Elf</source>
				<text type="formattedtext">
					<p>You have proficiency in the Perception skill.</p>
				</text>
				<type type="string">racial</type>
			</id-00002>
			<id-00003>
				<locked type="number">1</locked>
				<name type="string">Fey Ancestry</name>
				<source type="string">Elf</source>
				<text type="formattedtext">
					<p>You have advantage on saving throws against being charmed, and magic can't put you to sleep.</p>
				</text>
				<type type="string">racial</type>
			</id-00003>
			<id-00004>
				<locked type="number">1</locked>
				<name type="string">Blessing of the Raven Queen</name>
				<source type="string">Shadar-kai</source>
				<text type="formattedtext">
					<p>As a bonus action, you can magically teleport up to 30 feet to an unoccupied space you can see. Once you use this trait, you can't do so again until you finish a long rest.</p>
					<p>Starting at 3rd level, you also gain resistance to all damage when you teleport using this trait. The resistance lasts until the start of your next turn. During that time, you appear ghostly and translucent.</p>
				</text>
				<type type="string">subracial</type>
			</id-00004>
			<id-00005>
				<locked type="number">1</locked>
				<name type="string">Necrotic Resistance</name>
				<source type="string">Shadar-kai</source>
				<text type="formattedtext">
					<p>You have resistance to necrotic damage.</p>
				</text>
				<type type="string">subracial</type>
			</id-00005>
		</traitlist>
		<weaponlist>
			<id-00001>
				<attackbonus type="number">0</attackbonus>
				<attackstat type="string">dexterity</attackstat>
				<carried type="number">2</carried>
				<damagelist>
					<id-00001>
						<bonus type="number">0</bonus>
						<dice type="dice">d6</dice>
						<stat type="string">dexterity</stat>
						<statmult type="number">1</statmult>
						<type type="string">piercing</type>
					</id-00001>
				</damagelist>
				<isidentified type="number">1</isidentified>
				<maxammo type="number">0</maxammo>
				<name type="string">Shortsword</name>
				<prof type="number">1</prof>
				<properties type="string">Finesse, light</properties>
				<shortcut type="windowreference">
					<class>item</class>
					<recordname>....inventorylist.id-00002</recordname>
				</shortcut>
				<type type="number">0</type>
			</id-00001>
			<id-00002>
				<attackbonus type="number">0</attackbonus>
				<attackstat type="string">dexterity</attackstat>
				<carried type="number">1</carried>
				<damagelist>
					<id-00001>
						<bonus type="number">0</bonus>
						<dice type="dice">d6</dice>
						<stat type="string">base</stat>
						<statmult type="number">1</statmult>
						<type type="string">piercing</type>
					</id-00001>
				</damagelist>
				<maxammo type="number">0</maxammo>
				<name type="string">Shortsword left</name>
				<prof type="number">0</prof>
				<shortcut type="windowreference">
					<class></class>
					<recordname></recordname>
				</shortcut>
				<type type="number">0</type>
			</id-00002>
			<id-00003>
				<attackbonus type="number">0</attackbonus>
				<carried type="number">1</carried>
				<damagelist>
					<id-00001>
						<bonus type="number">0</bonus>
						<dice type="dice">d6</dice>
						<stat type="string">base</stat>
						<type type="string">piercing</type>
					</id-00001>
				</damagelist>
				<isidentified type="number">1</isidentified>
				<maxammo type="number">20</maxammo>
				<name type="string">Shortbow</name>
				<prof type="number">1</prof>
				<properties type="string">Ammunition (range 80/320), two-handed</properties>
				<shortcut type="windowreference">
					<class>item</class>
					<recordname>....inventorylist.id-00004</recordname>
				</shortcut>
				<type type="number">1</type>
			</id-00003>
		</weaponlist>
	</character>
</root>
