<?xml version="1.0" encoding="iso-8859-1"?>
<root version="3.3" release="8|CoreRPG:3">
	<character>
		<abilities>
			<charisma>
				<bonus type="number">3</bonus>
				<save type="number">3</save>
				<savemodifier type="number">0</savemodifier>
				<saveprof type="number">0</saveprof>
				<score type="number">16</score>
			</charisma>
			<constitution>
				<bonus type="number">2</bonus>
				<save type="number">2</save>
				<savemodifier type="number">0</savemodifier>
				<saveprof type="number">0</saveprof>
				<score type="number">14</score>
			</constitution>
			<dexterity>
				<bonus type="number">5</bonus>
				<save type="number">7</save>
				<savemodifier type="number">0</savemodifier>
				<saveprof type="number">1</saveprof>
				<score type="number">20</score>
			</dexterity>
			<intelligence>
				<bonus type="number">2</bonus>
				<save type="number">4</save>
				<savemodifier type="number">0</savemodifier>
				<saveprof type="number">1</saveprof>
				<score type="number">14</score>
			</intelligence>
			<strength>
				<bonus type="number">1</bonus>
				<save type="number">1</save>
				<savemodifier type="number">0</savemodifier>
				<saveprof type="number">0</saveprof>
				<score type="number">13</score>
			</strength>
			<wisdom>
				<bonus type="number">-1</bonus>
				<save type="number">-1</save>
				<savemodifier type="number">0</savemodifier>
				<saveprof type="number">0</saveprof>
				<score type="number">9</score>
			</wisdom>
		</abilities>
		<adventurelist>
		</adventurelist>
		<age type="string">20</age>
		<alignment type="string">Neutral Good</alignment>
		<appearance type="string">Guapo</appearance>
		<background type="string">Charlatan</background>
		<backgroundlink type="windowreference">
			<class>reference_background</class>
			<recordname>reference.backgrounddata.charlatan@DD PHB Deluxe</recordname>
		</backgroundlink>
		<classes>
			<id-00001>
				<casterlevelinvmult type="number">0</casterlevelinvmult>
				<casterpactmagic type="number">0</casterpactmagic>
				<hddie type="dice">d8</hddie>
				<hdused type="number">1</hdused>
				<level type="number">4</level>
				<name type="string">Rogue</name>
				<shortcut type="windowreference">
					<class>reference_class</class>
					<recordname>reference.classdata.rogue@D&#38;D Sword Coast Adventurer's Guide - Player's Guide</recordname>
				</shortcut>
			</id-00001>
		</classes>
		<coins>
			<slot1>
				<amount type="number">320</amount>
				<name type="string">gp</name>
			</slot1>
			<slot2>
				<amount type="number">0</amount>
			</slot2>
			<slot3>
				<amount type="number">0</amount>
			</slot3>
			<slot4>
				<amount type="number">0</amount>
			</slot4>
			<slot5>
				<amount type="number">0</amount>
			</slot5>
			<slot6>
				<amount type="number">0</amount>
			</slot6>
		</coins>
		<defenses>
			<ac>
				<armor type="number">2</armor>
				<disstealth type="number">0</disstealth>
				<misc type="number">0</misc>
				<prof type="number">1</prof>
				<shield type="number">0</shield>
				<temporary type="number">0</temporary>
				<total type="number">17</total>
			</ac>
		</defenses>
		<effectlist>
		</effectlist>
		<encumbrance>
			<encumbered type="number">65</encumbered>
			<encumberedheavy type="number">130</encumberedheavy>
			<liftpushdrag type="number">390</liftpushdrag>
			<load type="number">67</load>
			<max type="number">195</max>
		</encumbrance>
		<exp type="number">4203</exp>
		<expneeded type="number">6500</expneeded>
		<featlist>
			<id-00001>
				<locked type="number">1</locked>
				<name type="string">Defensive Duelist</name>
				<prerequisite type="string">Dexterity 13 or higher</prerequisite>
				<text type="formattedtext">
					<p><i>Prerequisite: Dexterity 13 or higher</i></p>
					<p>When you are wielding a finesse weapon with which you are proficient and another creature hits you with a melee attack, you can use your reaction to add your proficiency bonus to your AC for that attack, potentially causing the attack to miss you.</p>
				</text>
			</id-00001>
		</featlist>
		<featurelist>
			<id-00001>
				<locked type="number">1</locked>
				<name type="string">False Identity</name>
				<source type="string">Charlatan</source>
				<text type="formattedtext">
					<p>You have created a second identity that includes documentation, established acquaintances, and disguises that allow you to assume that persona.</p>
					<p>Additionally, you can forge documents including official papers and personal letters, as long as you have seen an example of the kind of document or the handwriting you are trying to copy.</p>
				</text>
			</id-00001>
			<id-00002>
				<level type="number">1</level>
				<locked type="number">1</locked>
				<name type="string">Expertise</name>
				<source type="string">Rogue</source>
				<text type="formattedtext">
					<p>At 1st level, choose two of your skill proficiencies, or one of your skill proficiencies and your proficiency with thieves' tools. Your proficiency bonus is doubled for any ability check you make that uses either of the chosen proficiencies.</p>
					<p>At 6th level, you can choose two more of your proficiencies (in skills or with thieves' tools) to gain this benefit.</p>
				</text>
			</id-00002>
			<id-00003>
				<level type="number">1</level>
				<locked type="number">1</locked>
				<name type="string">Thieves' Cant</name>
				<source type="string">Rogue</source>
				<text type="formattedtext">
					<p>During your rogue training you learned thieves' cant, a secret mix of dialect, jargon, and code that allows you to hide messages in seemingly normal conversation. Only another creature that knows thieves' cant understands such messages. It takes four times longer to convey such a message than it does to speak the same idea plainly.</p>
					<p>In addition, you understand a set of secret signs and symbols used to convey short, simple messages, such as whether an area is dangerous or the territory of a thieves' guild, whether loot is nearby, or whether the people in an area are easy marks or will provide a safe house for thieves on the run.</p>
				</text>
			</id-00003>
			<id-00004>
				<level type="number">1</level>
				<locked type="number">1</locked>
				<name type="string">Sneak Attack</name>
				<source type="string">Rogue</source>
				<text type="formattedtext">
					<p>Beginning at 1st level, you know how to strike subtly and exploit a foe's distraction. Once per turn, you can deal an extra 1d6 damage to one creature you hit with an attack if you have advantage on the attack roll. The attack must use a finesse or a ranged weapon.</p>
					<p>You don't need advantage on the attack roll if another enemy of the target is within 5 feet of it, that enemy isn't incapacitated, and you don't have disadvantage on the attack roll.</p>
					<p>The amount of the extra damage increases as you gain levels in this class, as shown in the Sneak Attack column of the Rogue table.</p>
				</text>
			</id-00004>
			<id-00005>
				<level type="number">2</level>
				<locked type="number">1</locked>
				<name type="string">Cunning Action</name>
				<source type="string">Rogue</source>
				<text type="formattedtext">
					<p>Starting at 2nd level, your quick thinking and agility allow you to move and act quickly. You can take a bonus action on each of your turns in combat. This action can be used only to take the Dash, Disengage, or Hide action.</p>
				</text>
			</id-00005>
			<id-00006>
				<level type="number">1</level>
				<locked type="number">1</locked>
				<name type="string">Swashbuckler</name>
				<source type="string">Rogue</source>
				<text type="formattedtext">
					<p>You focus your training on the art of the blade, relying on speed, elegance, and charm in equal parts. While some warriors are brutes clad in heavy armor, your method of fighting looks almost like a performance. Duelists and pirates typically belong to this archetype.</p>
					<p>A Swashbuckler excels in single combat, and can fight with two weapons while safely darting away from an opponent.</p>
					<p><b>Swashbucklers and Two-Weapon Fighting</b></p>
					<p>The Swashbuckler relies on a good understanding of the D&#38;D rules to realize its potential, specifically when it comes to fighting with two weapons. Other characters must use an action to Disengage if they want to escape a melee, but the Fancy Footwork feature of the Swashbuckler bundles a more limited version of Disengage within your attack. This allows you to use your bonus action to fight with two weapons, and then safely evade each foe you attacked.</p>
					<h>Features</h>
					<linklist>
						<link class="reference_classfeature" recordname="reference.classdata.rogue.features.fancyfootwork3@D&#38;D Sword Coast Adventurer's Guide - Player's Guide">Fancy Footwork</link>
						<link class="reference_classfeature" recordname="reference.classdata.rogue.features.rakishaudacity3@D&#38;D Sword Coast Adventurer's Guide - Player's Guide">Rakish Audacity</link>
						<link class="reference_classfeature" recordname="reference.classdata.rogue.features.panache9@D&#38;D Sword Coast Adventurer's Guide - Player's Guide">Panache</link>
						<link class="reference_classfeature" recordname="reference.classdata.rogue.features.elegantmaneuver13@D&#38;D Sword Coast Adventurer's Guide - Player's Guide">Elegant Maneuver</link>
						<link class="reference_classfeature" recordname="reference.classdata.rogue.features.masterduelist17@D&#38;D Sword Coast Adventurer's Guide - Player's Guide">Master Duelist</link>
					</linklist>
				</text>
			</id-00006>
			<id-00007>
				<level type="number">3</level>
				<locked type="number">1</locked>
				<name type="string">Rakish Audacity</name>
				<source type="string">Rogue</source>
				<specialization type="string">Swashbuckler</specialization>
				<text type="formattedtext">
					<p>Starting at 3rd level, your unmistakable confidence propels you into battle. You can add your Charisma modifier to your initiative rolls.</p>
					<p>In addition, you don't need advantage on your attack roll to use your Sneak Attack if no creature other than your target is within 5 feet of you. All the other rules for the Sneak Attack class feature still apply to you.</p>
				</text>
			</id-00007>
			<id-00008>
				<level type="number">3</level>
				<locked type="number">1</locked>
				<name type="string">Fancy Footwork</name>
				<source type="string">Rogue</source>
				<specialization type="string">Swashbuckler</specialization>
				<text type="formattedtext">
					<p>When you choose this archetype at 3rd level, you learn how to land a strike and then slip away without reprisal. During your turn, if you make a melee attack against a creature, that creature can't make opportunity attacks against you for the rest of your turn.</p>
				</text>
			</id-00008>
			<id-00009>
				<level type="number">4</level>
				<locked type="number">1</locked>
				<name type="string">Ability Score Improvement</name>
				<source type="string">Rogue</source>
				<text type="formattedtext">
					<p>When you reach 4th level, and again at 8th, 10th, 12th, 16th, and 19th level, you can increase one ability score of your choice by 2, or you can increase two ability scores of your choice by 1. As normal, you can't increase an ability score above 20 using this feature.</p>
				</text>
			</id-00009>
		</featurelist>
		<flaws type="string">A powerful person killed someone I love. Some day soon, I'll have my revenge.I hate to admit it and will hate myself for it, but I'll run and preserve my own hide if the going gets tough.</flaws>
		<gender type="string">Male</gender>
		<height type="string">1.80</height>
		<hp>
			<deathsavefail type="number">3</deathsavefail>
			<deathsavesuccess type="number">1</deathsavesuccess>
			<temporary type="number">0</temporary>
			<total type="number">33</total>
			<wounds type="number">33</wounds>
		</hp>
		<ideals type="string">Friendship. Material goods come and go. Bonds of friendship last forever. (Good)</ideals>
		<initiative>
			<misc type="number">5</misc>
			<temporary type="number">0</temporary>
			<total type="number">10</total>
		</initiative>
		<inventorylist>
			<id-00001>
				<ac type="number">12</ac>
				<bonus type="number">0</bonus>
				<carried type="number">2</carried>
				<cost type="string">45 gp</cost>
				<count type="number">1</count>
				<description type="formattedtext">
					<p>Made from supple and thin materials, light armor favors agile adventurers since it offers some protection without sacrificing mobility. If you wear light armor, you add your Dexterity modifier to the base number from your armor type to determine your Armor Class.</p>
					<p>Made from tough but flexible leather, studded leather is reinforced with close-set rivets or spikes.</p>
				</description>
				<dexbonus type="string">Yes</dexbonus>
				<isidentified type="number">1</isidentified>
				<locked type="number">1</locked>
				<name type="string">Studded Leather</name>
				<stealth type="string">-</stealth>
				<strength type="string">-</strength>
				<subtype type="string">Light Armor</subtype>
				<type type="string">Armor</type>
				<weight type="number">13</weight>
			</id-00001>
			<id-00002>
				<carried type="number">2</carried>
				<cost type="string">10 gp</cost>
				<count type="number">2</count>
				<damage type="string">1d6 piercing</damage>
				<description type="formattedtext">
					<p></p>
				</description>
				<isidentified type="number">1</isidentified>
				<locked type="number">1</locked>
				<name type="string">Shortsword</name>
				<properties type="string">Finesse, light</properties>
				<subtype type="string">Martial Weapons</subtype>
				<type type="string">Weapon</type>
				<weight type="number">2</weight>
			</id-00002>
			<id-00003>
				<carried type="number">2</carried>
				<cost type="string">2 gp</cost>
				<count type="number">3</count>
				<damage type="string">1d4 piercing</damage>
				<isidentified type="number">1</isidentified>
				<locked type="number">1</locked>
				<name type="string">Dagger</name>
				<properties type="string">Finesse, light, thrown (range 20/60)</properties>
				<subtype type="string">Simple Melee Weapons</subtype>
				<type type="string">Weapon</type>
				<weight type="number">1</weight>
			</id-00003>
			<id-00004>
				<carried type="number">1</carried>
				<cost type="string">5 cp</cost>
				<count type="number">10</count>
				<isidentified type="number">1</isidentified>
				<locked type="number">1</locked>
				<name type="string">Piton</name>
				<subtype type="string">Standard</subtype>
				<type type="string">Adventuring Gear</type>
				<weight type="number">0.25</weight>
			</id-00004>
			<id-00005>
				<carried type="number">1</carried>
				<cost type="string">5 sp</cost>
				<count type="number">6</count>
				<description type="formattedtext">
					<p>Rations consist of dry foods suitable for extended travel, including jerky, dried fruit, hardtack, and nuts.</p>
				</description>
				<isidentified type="number">1</isidentified>
				<locked type="number">1</locked>
				<name type="string">Rations (1 Day)</name>
				<subtype type="string">Standard</subtype>
				<type type="string">Adventuring Gear</type>
				<weight type="number">2</weight>
			</id-00005>
			<id-00006>
				<carried type="number">1</carried>
				<cost type="string">2 sp</cost>
				<count type="number">1</count>
				<effectlist>
				</effectlist>
				<isidentified type="number">1</isidentified>
				<locked type="number">1</locked>
				<name type="string">Waterskin</name>
				<subtype type="string">Standard</subtype>
				<type type="string">Adventuring Gear</type>
				<weight type="number">5</weight>
			</id-00006>
			<id-00007>
				<carried type="number">1</carried>
				<cost type="string">2 gp</cost>
				<count type="number">1</count>
				<isidentified type="number">1</isidentified>
				<locked type="number">1</locked>
				<name type="string">Backpack (Empty)</name>
				<subtype type="string">Standard</subtype>
				<type type="string">Adventuring Gear</type>
				<weight type="number">5</weight>
			</id-00007>
			<id-00008>
				<carried type="number">1</carried>
				<cost type="string">1 gp</cost>
				<count type="number">1</count>
				<isidentified type="number">1</isidentified>
				<locked type="number">1</locked>
				<name type="string">Hammer</name>
				<subtype type="string">Standard</subtype>
				<type type="string">Adventuring Gear</type>
				<weight type="number">3</weight>
			</id-00008>
			<id-00009>
				<carried type="number">1</carried>
				<cost type="string">1 cp</cost>
				<count type="number">8</count>
				<description type="formattedtext">
					<p>A torch burns for 1 hour, providing bright light in a 20-foot radius and dim light for an additional 20 feet. If you make a melee attack with a burning torch and hit, it deals 1 fire damage.</p>
				</description>
				<isidentified type="number">1</isidentified>
				<locked type="number">1</locked>
				<name type="string">Torch</name>
				<subtype type="string">Standard</subtype>
				<type type="string">Adventuring Gear</type>
				<weight type="number">1</weight>
			</id-00009>
			<id-00010>
				<carried type="number">1</carried>
				<cost type="string">5 sp</cost>
				<count type="number">1</count>
				<description type="formattedtext">
					<p>This small container holds flint, fire steel, and tinder (usually dry cloth soaked in light oil) used to kindle a fire. Using it to light a torch-or anything else with abundant, exposed fuel-takes an action. Lighting any other fire takes 1 minute.</p>
				</description>
				<isidentified type="number">1</isidentified>
				<locked type="number">1</locked>
				<name type="string">Tinderbox</name>
				<subtype type="string">Standard</subtype>
				<type type="string">Adventuring Gear</type>
				<weight type="number">1</weight>
			</id-00010>
			<id-00011>
				<carried type="number">2</carried>
				<cost type="string">25 gp</cost>
				<count type="number">1</count>
				<damage type="string">1d6 piercing</damage>
				<effectlist>
				</effectlist>
				<isidentified type="number">1</isidentified>
				<locked type="number">1</locked>
				<name type="string">Shortbow</name>
				<properties type="string">Ammunition (range 80/320), two-handed</properties>
				<subtype type="string">Simple Ranged Weapons</subtype>
				<type type="string">Weapon</type>
				<weight type="number">2</weight>
			</id-00011>
			<id-00012>
				<carried type="number">0</carried>
				<cost type="string">1 gp</cost>
				<count type="number">1</count>
				<isidentified type="number">1</isidentified>
				<locked type="number">1</locked>
				<name type="string">Rope, Hempen (50 Feet)</name>
				<subtype type="string">Standard</subtype>
				<type type="string">Adventuring Gear</type>
				<weight type="number">10</weight>
			</id-00012>
			<id-00014>
				<ac type="number">0</ac>
				<bonus type="number">0</bonus>
				<carried type="number">1</carried>
				<cost type="string">1 gp</cost>
				<count type="number">1</count>
				<description type="formattedtext">
					<p></p>
				</description>
				<effectlist>
				</effectlist>
				<isidentified type="number">1</isidentified>
				<locked type="number">1</locked>
				<name type="string">Bedroll</name>
				<subtype type="string">Standard</subtype>
				<type type="string">Adventuring Gear</type>
				<weight type="number">4</weight>
			</id-00014>
			<id-00015>
				<carried type="number">2</carried>
				<cost type="string">2 gp</cost>
				<count type="number">1</count>
				<description type="formattedtext">
					<p></p>
				</description>
				<isidentified type="number">1</isidentified>
				<locked type="number">1</locked>
				<name type="string">Clothes, Traveler's</name>
				<subtype type="string">Standard</subtype>
				<type type="string">Adventuring Gear</type>
				<weight type="number">4</weight>
			</id-00015>
			<id-00016>
				<ac type="number">0</ac>
				<bonus type="number">0</bonus>
				<carried type="number">2</carried>
				<cost type="string">50 gp</cost>
				<count type="number">0</count>
				<description type="formattedtext">
					<p>A character who drinks the magical red fluid in this vial regains 2d4 + 2 hit points. Drinking or administering a potion takes an action.</p>
				</description>
				<effectlist>
				</effectlist>
				<isidentified type="number">1</isidentified>
				<locked type="number">1</locked>
				<name type="string">Potion Of Healing</name>
				<subtype type="string">Standard</subtype>
				<type type="string">Adventuring Gear</type>
				<weight type="number">0.5</weight>
			</id-00016>
		</inventorylist>
		<languagelist>
			<id-00001>
				<name type="string">Common</name>
			</id-00001>
			<id-00002>
				<name type="string">Elvish</name>
			</id-00002>
		</languagelist>
		<level type="number">4</level>
		<name type="string">Kallash</name>
		<notes type="string">I cheat at games of chance.</notes>
		<perception type="number">9</perception>
		<perceptionmodifier type="number">0</perceptionmodifier>
		<personalitytraits type="string">I lie about almost everything, even when there's no good reason to.</personalitytraits>
		<powermeta>
			<pactmagicslots1>
				<max type="number">0</max>
				<used type="number">0</used>
			</pactmagicslots1>
			<pactmagicslots2>
				<max type="number">0</max>
				<used type="number">0</used>
			</pactmagicslots2>
			<pactmagicslots3>
				<max type="number">0</max>
				<used type="number">0</used>
			</pactmagicslots3>
			<pactmagicslots4>
				<max type="number">0</max>
				<used type="number">0</used>
			</pactmagicslots4>
			<pactmagicslots5>
				<max type="number">0</max>
				<used type="number">0</used>
			</pactmagicslots5>
			<pactmagicslots6>
				<max type="number">0</max>
				<used type="number">0</used>
			</pactmagicslots6>
			<pactmagicslots7>
				<max type="number">0</max>
				<used type="number">0</used>
			</pactmagicslots7>
			<pactmagicslots8>
				<max type="number">0</max>
				<used type="number">0</used>
			</pactmagicslots8>
			<pactmagicslots9>
				<max type="number">0</max>
				<used type="number">0</used>
			</pactmagicslots9>
			<spellslots1>
				<max type="number">0</max>
				<used type="number">0</used>
			</spellslots1>
			<spellslots2>
				<max type="number">0</max>
				<used type="number">0</used>
			</spellslots2>
			<spellslots3>
				<max type="number">0</max>
				<used type="number">0</used>
			</spellslots3>
			<spellslots4>
				<max type="number">0</max>
				<used type="number">0</used>
			</spellslots4>
			<spellslots5>
				<max type="number">0</max>
				<used type="number">0</used>
			</spellslots5>
			<spellslots6>
				<max type="number">0</max>
				<used type="number">0</used>
			</spellslots6>
			<spellslots7>
				<max type="number">0</max>
				<used type="number">0</used>
			</spellslots7>
			<spellslots8>
				<max type="number">0</max>
				<used type="number">0</used>
			</spellslots8>
			<spellslots9>
				<max type="number">0</max>
				<used type="number">0</used>
			</spellslots9>
		</powermeta>
		<powermode type="string">standard</powermode>
		<powers>
			<id-00002>
				<actions>
					<id-00001>
						<apply type="string">roll</apply>
						<durmod type="number">0</durmod>
						<label type="string">Sneak Attack; DMG: 2d6</label>
						<order type="number">1</order>
						<targeting type="string">self</targeting>
						<type type="string">effect</type>
					</id-00001>
				</actions>
				<cast type="number">0</cast>
				<level type="number">0</level>
				<name type="string">Sneak Attack</name>
				<prepared type="number">0</prepared>
			</id-00002>
		</powers>
		<profbonus type="number">2</profbonus>
		<proficiencylist>
			<id-00001>
				<name type="string">Tool: Disguise kit, forgery kit</name>
			</id-00001>
			<id-00002>
				<name type="string">Weapon: Simple weapons, hand crossbows, longswords, rapiers, shortswords</name>
			</id-00002>
			<id-00003>
				<name type="string">Tool: Thieves' tools</name>
			</id-00003>
			<id-00004>
				<name type="string">Armor: Light armor</name>
			</id-00004>
		</proficiencylist>
		<race type="string">Human-Variant</race>
		<racelink type="windowreference">
			<class>reference_race</class>
			<recordname>reference.racedata.human_variant@DD PHB Deluxe</recordname>
		</racelink>
		<size type="string">Medium</size>
		<skilllist>
			<id-00001>
				<misc type="number">0</misc>
				<name type="string">Perception</name>
				<prof type="number">0</prof>
				<stat type="string">wisdom</stat>
				<total type="number">-1</total>
			</id-00001>
			<id-00002>
				<misc type="number">0</misc>
				<name type="string">Arcana</name>
				<prof type="number">0</prof>
				<stat type="string">intelligence</stat>
				<total type="number">2</total>
			</id-00002>
			<id-00003>
				<misc type="number">0</misc>
				<name type="string">Persuasion</name>
				<prof type="number">0</prof>
				<stat type="string">charisma</stat>
				<total type="number">3</total>
			</id-00003>
			<id-00004>
				<misc type="number">0</misc>
				<name type="string">Nature</name>
				<prof type="number">0</prof>
				<stat type="string">intelligence</stat>
				<total type="number">2</total>
			</id-00004>
			<id-00005>
				<misc type="number">0</misc>
				<name type="string">Medicine</name>
				<prof type="number">0</prof>
				<stat type="string">wisdom</stat>
				<total type="number">-1</total>
			</id-00005>
			<id-00006>
				<misc type="number">0</misc>
				<name type="string">Survival</name>
				<prof type="number">0</prof>
				<stat type="string">wisdom</stat>
				<total type="number">-1</total>
			</id-00006>
			<id-00007>
				<misc type="number">0</misc>
				<name type="string">Performance</name>
				<prof type="number">0</prof>
				<stat type="string">charisma</stat>
				<total type="number">3</total>
			</id-00007>
			<id-00008>
				<misc type="number">0</misc>
				<name type="string">Acrobatics</name>
				<prof type="number">1</prof>
				<stat type="string">dexterity</stat>
				<total type="number">7</total>
			</id-00008>
			<id-00009>
				<misc type="number">0</misc>
				<name type="string">Religion</name>
				<prof type="number">0</prof>
				<stat type="string">intelligence</stat>
				<total type="number">2</total>
			</id-00009>
			<id-00010>
				<misc type="number">0</misc>
				<name type="string">Athletics</name>
				<prof type="number">1</prof>
				<stat type="string">strength</stat>
				<total type="number">3</total>
			</id-00010>
			<id-00011>
				<misc type="number">0</misc>
				<name type="string">Sleight of Hand</name>
				<prof type="number">1</prof>
				<stat type="string">dexterity</stat>
				<total type="number">7</total>
			</id-00011>
			<id-00012>
				<misc type="number">0</misc>
				<name type="string">Insight</name>
				<prof type="number">0</prof>
				<stat type="string">wisdom</stat>
				<total type="number">-1</total>
			</id-00012>
			<id-00013>
				<misc type="number">0</misc>
				<name type="string">Intimidation</name>
				<prof type="number">2</prof>
				<stat type="string">charisma</stat>
				<total type="number">7</total>
			</id-00013>
			<id-00014>
				<misc type="number">0</misc>
				<name type="string">Deception</name>
				<prof type="number">1</prof>
				<stat type="string">charisma</stat>
				<total type="number">5</total>
			</id-00014>
			<id-00015>
				<misc type="number">0</misc>
				<name type="string">Investigation</name>
				<prof type="number">1</prof>
				<stat type="string">intelligence</stat>
				<total type="number">4</total>
			</id-00015>
			<id-00016>
				<misc type="number">0</misc>
				<name type="string">Stealth</name>
				<prof type="number">2</prof>
				<stat type="string">dexterity</stat>
				<total type="number">9</total>
			</id-00016>
			<id-00017>
				<misc type="number">0</misc>
				<name type="string">History</name>
				<prof type="number">0</prof>
				<stat type="string">intelligence</stat>
				<total type="number">2</total>
			</id-00017>
			<id-00018>
				<misc type="number">0</misc>
				<name type="string">Animal Handling</name>
				<prof type="number">0</prof>
				<stat type="string">wisdom</stat>
				<total type="number">-1</total>
			</id-00018>
			<id-00019>
				<misc type="number">0</misc>
				<name type="string">Thieves tools (pick locks)</name>
				<prof type="number">1</prof>
				<stat type="string">dexterity</stat>
				<total type="number">7</total>
			</id-00019>
			<id-00020>
				<misc type="number">0</misc>
				<name type="string">Thieves tools (disarm traps)</name>
				<prof type="number">1</prof>
				<stat type="string">intelligence</stat>
				<total type="number">4</total>
			</id-00020>
		</skilllist>
		<speed>
			<armor type="number">0</armor>
			<base type="number">30</base>
			<misc type="number">0</misc>
			<temporary type="number">-10</temporary>
			<total type="number">20</total>
		</speed>
		<temp>
		</temp>
		<token type="token">portrait_id-00011_token</token>
		<traitlist>
			<id-00001>
				<locked type="number">1</locked>
				<name type="string">Skills</name>
				<source type="string">Human-Variant</source>
				<text type="formattedtext">
					<p>You gain proficiency in one skill of your choice.</p>
				</text>
				<type type="string">racial</type>
			</id-00001>
			<id-00002>
				<locked type="number">1</locked>
				<name type="string">Feat</name>
				<source type="string">Human-Variant</source>
				<text type="formattedtext">
					<p>You gain one feat of your choice.</p>
				</text>
				<type type="string">racial</type>
			</id-00002>
		</traitlist>
		<weapon>
			<critdicebonus>
			</critdicebonus>
			<critrange>
				<melee type="number">20</melee>
				<ranged type="number">20</ranged>
			</critrange>
		</weapon>
		<weaponlist>
			<id-00001>
				<attackstat type="string">dexterity</attackstat>
				<carried type="number">2</carried>
				<damagelist>
					<id-00001>
						<dice type="dice">d6</dice>
						<stat type="string">dexterity</stat>
						<type type="string">piercing</type>
					</id-00001>
				</damagelist>
				<isidentified type="number">1</isidentified>
				<maxammo type="number">0</maxammo>
				<name type="string">Shortsword</name>
				<prof type="number">1</prof>
				<shortcut type="windowreference">
					<class>item</class>
					<recordname>....inventorylist.id-00002</recordname>
				</shortcut>
				<type type="number">0</type>
			</id-00001>
			<id-00002>
				<attackstat type="string">dexterity</attackstat>
				<carried type="number">2</carried>
				<damagelist>
					<id-00001>
						<dice type="dice">d4</dice>
						<stat type="string">dexterity</stat>
						<type type="string">piercing</type>
					</id-00001>
				</damagelist>
				<isidentified type="number">1</isidentified>
				<maxammo type="number">0</maxammo>
				<name type="string">Dagger</name>
				<prof type="number">1</prof>
				<shortcut type="windowreference">
					<class>item</class>
					<recordname>....inventorylist.id-00003</recordname>
				</shortcut>
				<type type="number">0</type>
			</id-00002>
			<id-00003>
				<attackstat type="string">dexterity</attackstat>
				<carried type="number">2</carried>
				<damagelist>
					<id-00001>
						<dice type="dice">d4</dice>
						<stat type="string">dexterity</stat>
						<type type="string">piercing</type>
					</id-00001>
				</damagelist>
				<isidentified type="number">1</isidentified>
				<maxammo type="number">0</maxammo>
				<name type="string">Dagger</name>
				<prof type="number">1</prof>
				<shortcut type="windowreference">
					<class>item</class>
					<recordname>....inventorylist.id-00003</recordname>
				</shortcut>
				<type type="number">2</type>
			</id-00003>
			<id-00004>
				<attackbonus type="number">0</attackbonus>
				<attackstat type="string">dexterity</attackstat>
				<carried type="number">1</carried>
				<damagelist>
					<id-00001>
						<bonus type="number">0</bonus>
						<dice type="dice">d6</dice>
						<type type="string">piercing</type>
					</id-00001>
				</damagelist>
				<maxammo type="number">0</maxammo>
				<name type="string">Shortsword (left)</name>
				<prof type="number">1</prof>
				<shortcut type="windowreference">
					<class></class>
					<recordname></recordname>
				</shortcut>
				<type type="number">0</type>
			</id-00004>
			<id-00005>
				<ammo type="number">4</ammo>
				<carried type="number">2</carried>
				<damagelist>
					<id-00001>
						<dice type="dice">d6</dice>
						<stat type="string">base</stat>
						<type type="string">piercing</type>
					</id-00001>
				</damagelist>
				<isidentified type="number">1</isidentified>
				<maxammo type="number">20</maxammo>
				<name type="string">Shortbow</name>
				<prof type="number">1</prof>
				<shortcut type="windowreference">
					<class>item</class>
					<recordname>....inventorylist.id-00011</recordname>
				</shortcut>
				<type type="number">1</type>
			</id-00005>
		</weaponlist>
		<weight type="string">75</weight>
	</character>
</root>
